odoo10_addon_shopinvader_membership-10.0.1.2.0-py3.8-nspkg.pth
odoo/addons/shopinvader_membership/README.rst
odoo/addons/shopinvader_membership/__init__.py
odoo/addons/shopinvader_membership/__manifest__.py
odoo/addons/shopinvader_membership/i18n/shopinvader_membership.pot
odoo/addons/shopinvader_membership/readme/CONTRIBUTORS.rst
odoo/addons/shopinvader_membership/readme/DESCRIPTION.rst
odoo/addons/shopinvader_membership/services/__init__.py
odoo/addons/shopinvader_membership/services/membership.py
odoo/addons/shopinvader_membership/services/membership_product.py
odoo/addons/shopinvader_membership/static/description/icon.png
odoo/addons/shopinvader_membership/static/description/index.html
odoo/addons/shopinvader_membership/tests/__init__.py
odoo/addons/shopinvader_membership/tests/test_membership_product_service.py
odoo/addons/shopinvader_membership/tests/test_membership_service.py
odoo10_addon_shopinvader_membership-10.0.1.2.0.dist-info/METADATA
odoo10_addon_shopinvader_membership-10.0.1.2.0.dist-info/WHEEL
odoo10_addon_shopinvader_membership-10.0.1.2.0.dist-info/namespace_packages.txt
odoo10_addon_shopinvader_membership-10.0.1.2.0.dist-info/top_level.txt
odoo10_addon_shopinvader_membership-10.0.1.2.0.dist-info/RECORD
